{
	"info": {
		"_postman_id": "a9a72c3b-a7a9-4039-8832-4112d129743c",
		"name": "E-commerce Backend",
		"schema": "https://schema.getpostman.com/json/collection/v2.1.0/collection.json",
		"description": "Postman collection for the E-commerce Backend API"
	},
	"item": [
		{
			"name": "Health Check",
			"request": {
				"method": "GET",
				"header": [],
				"url": {
					"raw": "{{baseUrl}}/api/health",
					"host": [
						"{{baseUrl}}"
					],
					"path": [
						"api",
						"health"
					]
				}
			},
			"response": []
		},
		{
			"name": "User",
			"item": [
				{
					"name": "Register",
					"request": {
						"method": "POST",
						"header": [],
						"body": {
							"mode": "raw",
							"raw": "{\n    \"email\": \"user@example.com\",\n    \"password\": \"password123\",\n    \"name\": \"Test User\"\n}",
							"options": {
								"raw": {
									"language": "json"
								}
							}
						},
						"url": {
							"raw": "{{baseUrl}}/api/v1/users/register",
							"host": [
								"{{baseUrl}}"
							],
							"path": [
								"api",
								"v1",
								"users",
								"register"
							]
						}
					},
					"response": []
				},
				{
					"name": "Login",
					"request": {
						"method": "POST",
						"header": [],
						"body": {
							"mode": "raw",
							"raw": "{\n    \"email\": \"user@example.com\",\n    \"password\": \"password123\"\n}",
							"options": {
								"raw": {
									"language": "json"
								}
							}
						},
						"url": {
							"raw": "{{baseUrl}}/api/v1/users/login",
							"host": [
								"{{baseUrl}}"
							],
							"path": [
								"api",
								"v1",
								"users",
								"login"
							]
						}
					},
					"response": []
				},
				{
					"name": "Get Profile",
					"request": {
						"method": "GET",
						"header": [
							{
								"key": "Authorization",
								"value": "Bearer {{token}}",
								"type": "text"
							}
						],
						"url": {
							"raw": "{{baseUrl}}/api/v1/users/profile",
							"host": [
								"{{baseUrl}}"
							],
							"path": [
								"api",
								"v1",
								"users",
								"profile"
							]
						}
					},
					"response": []
				},
				{
					"name": "Update Profile",
					"request": {
						"method": "PUT",
						"header": [
							{
								"key": "Authorization",
								"value": "Bearer {{token}}",
								"type": "text"
							}
						],
						"body": {
							"mode": "raw",
							"raw": "{\n    \"name\": \"Updated Name\"\n}",
							"options": {
								"raw": {
									"language": "json"
								}
							}
						},
						"url": {
							"raw": "{{baseUrl}}/api/v1/users/profile",
							"host": [
								"{{baseUrl}}"
							],
							"path": [
								"api",
								"v1",
								"users",
								"profile"
							]
						}
					},
					"response": []
				},
				{
					"name": "Change Password",
					"request": {
						"method": "PUT",
						"header": [
							{
								"key": "Authorization",
								"value": "Bearer {{token}}",
								"type": "text"
							}
						],
						"body": {
							"mode": "raw",
							"raw": "{\n    \"oldPassword\": \"password123\",\n    \"newPassword\": \"newpassword123\"\n}",
							"options": {
								"raw": {
									"language": "json"
								}
							}
						},
						"url": {
							"raw": "{{baseUrl}}/api/v1/users/change-password",
							"host": [
								"{{baseUrl}}"
							],
							"path": [
								"api",
								"v1",
								"users",
								"change-password"
							]
						}
					},
					"response": []
				},
				{
					"name": "Add Bank Details",
					"request": {
						"method": "POST",
						"header": [
							{
								"key": "Authorization",
								"value": "Bearer {{token}}",
								"type": "text"
							}
						],
						"body": {
							"mode": "raw",
							"raw": "{\n    \"accountNumber\": \"1234567890\",\n    \"ifscCode\": \"IFSC1234\",\n    \"bankName\": \"Test Bank\"\n}",
							"options": {
								"raw": {
									"language": "json"
								}
							}
						},
						"url": {
							"raw": "{{baseUrl}}/api/v1/users/bank-details",
							"host": [
								"{{baseUrl}}"
							],
							"path": [
								"api",
								"v1",
								"users",
								"bank-details"
							]
						}
					},
					"response": []
				},
				{
					"name": "Update Bank Details",
					"request": {
						"method": "PUT",
						"header": [
							{
								"key": "Authorization",
								"value": "Bearer {{token}}",
								"type": "text"
							}
						],
						"body": {
							"mode": "raw",
							"raw": "{\n    \"accountNumber\": \"0987654321\"\n}",
							"options": {
								"raw": {
									"language": "json"
								}
							}
						},
						"url": {
							"raw": "{{baseUrl}}/api/v1/users/bank-details",
							"host": [
								"{{baseUrl}}"
							],
							"path": [
								"api",
								"v1",
								"users",
								"bank-details"
							]
						}
					},
					"response": []
				},
				{
					"name": "Get Bank Details",
					"request": {
						"method": "GET",
						"header": [
							{
								"key": "Authorization",
								"value": "Bearer {{token}}",
								"type": "text"
							}
						],
						"url": {
							"raw": "{{baseUrl}}/api/v1/users/bank-details",
							"host": [
								"{{baseUrl}}"
							],
							"path": [
								"api",
								"v1",
								"users",
								"bank-details"
							]
						}
					},
					"response": []
				}
			]
		},
		{
			"name": "Admin",
			"item": [
				{
					"name": "Get All Users",
					"request": {
						"method": "GET",
						"header": [
							{
								"key": "Authorization",
								"value": "Bearer {{adminToken}}",
								"type": "text"
							}
						],
						"url": {
							"raw": "{{baseUrl}}/api/v1/admin/users",
							"host": [
								"{{baseUrl}}"
							],
							"path": [
								"api",
								"v1",
								"admin",
								"users"
							]
						}
					},
					"response": []
				},
				{
					"name": "Get User By Id",
					"request": {
						"method": "GET",
						"header": [
							{
								"key": "Authorization",
								"value": "Bearer {{adminToken}}",
								"type": "text"
							}
						],
						"url": {
							"raw": "{{baseUrl}}/api/v1/admin/users/:userId",
							"host": [
								"{{baseUrl}}"
							],
							"path": [
								"api",
								"v1",
								"admin",
								"users",
								":userId"
							],
							"variable": [
								{
									"key": "userId",
									"value": ""
								}
							]
						}
					},
					"response": []
				},
				{
					"name": "Update User Status",
					"request": {
						"method": "PUT",
						"header": [
							{
								"key": "Authorization",
								"value": "Bearer {{adminToken}}",
								"type": "text"
							}
						],
						"body": {
							"mode": "raw",
							"raw": "{\n    \"status\": \"active\"\n}",
							"options": {
								"raw": {
									"language": "json"
								}
							}
						},
						"url": {
							"raw": "{{baseUrl}}/api/v1/admin/users/:userId/status",
							"host": [
								"{{baseUrl}}"
							],
							"path": [
								"api",
								"v1",
								"admin",
								"users",
								":userId",
								"status"
							],
							"variable": [
								{
									"key": "userId",
									"value": ""
								}
							]
						}
					},
					"response": []
				},
				{
					"name": "Verify User",
					"request": {
						"method": "PUT",
						"header": [
							{
								"key": "Authorization",
								"value": "Bearer {{adminToken}}",
								"type": "text"
							}
						],
						"url": {
							"raw": "{{baseUrl}}/api/v1/admin/users/:userId/verify",
							"host": [
								"{{baseUrl}}"
							],
							"path": [
								"api",
								"v1",
								"admin",
								"users",
								":userId",
								"verify"
							],
							"variable": [
								{
									"key": "userId",
									"value": ""
								}
							]
						}
					},
					"response": []
				},
				{
					"name": "Delete User",
					"request": {
						"method": "DELETE",
						"header": [
							{
								"key": "Authorization",
								"value": "Bearer {{adminToken}}",
								"type": "text"
							}
						],
						"url": {
							"raw": "{{baseUrl}}/api/v1/admin/users/:userId",
							"host": [
								"{{baseUrl}}"
							],
							"path": [
								"api",
								"v1",
								"admin",
								"users",
								":userId"
							],
							"variable": [
								{
									"key": "userId",
									"value": ""
								}
							]
						}
					},
					"response": []
				},
				{
					"name": "Get All User Bank Details",
					"request": {
						"method": "GET",
						"header": [
							{
								"key": "Authorization",
								"value": "Bearer {{adminToken}}",
								"type": "text"
							}
						],
						"url": {
							"raw": "{{baseUrl}}/api/v1/admin/bank-details",
							"host": [
								"{{baseUrl}}"
							],
							"path": [
								"api",
								"v1",
								"admin",
								"bank-details"
							]
						}
					},
					"response": []
				},
				{
					"name": "Get User Bank Details",
					"request": {
						"method": "GET",
						"header": [
							{
								"key": "Authorization",
								"value": "Bearer {{adminToken}}",
								"type": "text"
							}
						],
						"url": {
							"raw": "{{baseUrl}}/api/v1/admin/bank-details/:userId",
							"host": [
								"{{baseUrl}}"
							],
							"path": [
								"api",
								"v1",
								"admin",
								"bank-details",
								":userId"
							],
							"variable": [
								{
									"key": "userId",
									"value": ""
								}
							]
						}
					},
					"response": []
				}
			]
		}
	],
	"variable": [
		{
			"key": "baseUrl",
			"value": "http://localhost:3000",
			"type": "string"
		},
		{
			"key": "token",
			"value": "",
			"type": "string"
		},
		{
			"key": "adminToken",
			"value": "",
			"type": "string"
		}
	]
}